pgliveapp/__init__.py
pgliveapp/app.py
pgliveapp-0.1.6.dist-info/METADATA
pgliveapp-0.1.6.dist-info/WHEEL
pgliveapp-0.1.6.dist-info/entry_points.txt
pgliveapp-0.1.6.dist-info/licenses/LICENCE.txt
pgliveapp-0.1.6.dist-info/RECORD
