Metadata-Version: 2.4
Name: pgliveapp
Version: 0.1.6
Summary: A GUI application for pglive.
Author-email: takumi-nishimura <clp13218@nitech.jp>
License-File: LICENCE.txt
Requires-Python: >=3.9
Requires-Dist: pglive>=0.8.0
Requires-Dist: pyqt6>=6.8.0
